{
  "$schema": "https://mintlify.com/docs.json",
  "theme": "mint",
  "name": "Eurocode Docs",
  "colors": {
    "primary": "#16A34A",
    "light": "#07C983",
    "dark": "#15803D"
  },
  "favicon": "/favicon.svg",
  "navigation": {
    "tabs": [
      {
        "tab": "Guides",
        "groups": [
          {
            "group": "Eurocode 1 - Actions on Structures",
            "pages": [
              "ec1/overview",
              "ec1/part1-1-general-actions"
            ]
          },
          {
            "group": "Eurocode 2 - Design of Concrete Structures",
            "pages": [
              "ec2/overview",
              "ec2/part1-1-general-rules",
              "ec2/part1-2-fire-design",
              "ec2/part1-3-precast-elements",
              "ec2/part1-4-lightweight-concrete",
              "ec2/part1-5-unbonded-tendons",
              "ec2/part2-concrete-bridges",
              "ec2/part3-liquid-retaining",
              "ec2/part4-fastenings"
            ]
          },
          {
            "group": "Eurocode 3 - Design of Steel Structures",
            "pages": [
              "ec3/overview",
              "ec3/part1-1-general-rules",
              "ec3/part1-2-fire-design",
              "ec3/part1-3-cold-formed",
              "ec3/part1-4-stainless-steel",
              "ec3/part1-5-plated-elements",
              "ec3/part1-6-shell-structures",
              "ec3/part1-7-planar-plates",
              "ec3/part1-8-joints",
              "ec3/part1-9-fatigue",
              "ec3/part1-10-fracture-toughness",
              "ec3/part1-11-tension-members",
              "ec3/part1-12-high-strength-steel",
              "ec3/part1-13-web-openings",
              "ec3/part2-steel-bridges",
              "ec3/part3-1-towers-masts",
              "ec3/part3-2-chimneys",
              "ec3/part4-1-silos",
              "ec3/part4-2-tanks",
              "ec3/part4-3-pipelines",
              "ec3/part5-piling"
            ]
          }
        ]
      }
    ],
    "global": {
      "anchors": [
        {
          "anchor": "Official Eurocodes",
          "href": "https://eurocodes.jrc.ec.europa.eu/",
          "icon": "book-open-cover"
        }
      ]
    }
  },
  "logo": {
    "light": "/logo/light.svg",
    "dark": "/logo/dark.svg"
  },
  "navbar": {
    "links": [
      {
        "label": "Support",
        "href": "mailto:support@eurocodedocs.com"
      }
    ],
    "primary": {
      "type": "button",
      "label": "Calculator",
      "href": "https://calculator.eurocodedocs.com"
    }
  },
  "footer": {
    "socials": {
      "x": "https://x.com/eurocodedocs",
      "github": "https://github.com/eurocodedocs",
      "linkedin": "https://linkedin.com/company/eurocodedocs"
    }
  }
}